proxy_middleman/__init__.py
proxy_middleman/custom_exceptions.py
proxy_middleman/notification.py
proxy_middleman/proxy_rotation.py
proxy_middleman-0.0.25.dist-info/METADATA
proxy_middleman-0.0.25.dist-info/WHEEL
proxy_middleman-0.0.25.dist-info/top_level.txt
proxy_middleman-0.0.25.dist-info/RECORD
